pyfcr/__init__.py
pyfcr/_estimators.cp310-win_amd64.pyd
pyfcr/assaf.py
pyfcr/biometrics.py
pyfcr/config.py
pyfcr/fcr.py
pyfcr/fcr_base.py
pyfcr/utilities.py
pyfcr/version.py
pyfcr/AssafModel/__init__.py
pyfcr/AssafModel/read_simulated_data.py
pyfcr/AssafModel/run_model_B.py
pyfcr/AssafModel/run_model_B_2.py
pyfcr/AssafModel/simulations_run.py
pyfcr/AssafModel/single_run.py
PyFCR-1.3.dist-info/METADATA
PyFCR-1.3.dist-info/WHEEL
PyFCR-1.3.dist-info/top_level.txt
PyFCR-1.3.dist-info/RECORD
