Metadata-Version: 2.1
Name: PyFCR
Version: 1.3
Summary: A Python package for frailty-based multivariate survival data analysis with competing risks
Author: Danielle Poleg
Author-email: daniellepoleg@gmail.com
Requires-Python: ~=3.10
Requires-Dist: rpy2
Requires-Dist: numpy
Requires-Dist: pandas
Requires-Dist: ninja
Requires-Dist: cmake
Requires-Dist: matplotlib
